apple_data/__init__.py
apple_data/py.typed
share/.gitkeep
share/apns.json
share/backup.json
share/baseband/qualcomm/mav13.json
share/baseband/qualcomm/mav20.json
share/baseband/qualcomm/mav21.json
share/baseband.json
share/bluetooth.json
share/boot_args.json
share/bridgeos.json
share/bundles.json
share/coprocessor.json
share/cores.json
share/credits.json
share/debug.json
share/defaults.json
share/device_tree.json
"share/devices/ADP3,1.json"
"share/devices/ADP3,2.json"
"share/devices/AppleTV5,3.json"
"share/devices/AudioAccessory5,1.json"
"share/devices/VirtualMac2,1.json"
"share/devices/Watch3,1.json"
"share/devices/Watch3,2.json"
"share/devices/Watch3,3.json"
"share/devices/Watch3,4.json"
"share/devices/Watch4,1.json"
"share/devices/Watch4,2.json"
"share/devices/Watch4,3.json"
"share/devices/Watch4,4.json"
"share/devices/Watch5,1.json"
"share/devices/Watch5,10.json"
"share/devices/Watch5,11.json"
"share/devices/Watch5,12.json"
"share/devices/Watch5,2.json"
"share/devices/Watch5,3.json"
"share/devices/Watch5,4.json"
"share/devices/Watch5,9.json"
"share/devices/Watch6,1.json"
"share/devices/Watch6,2.json"
"share/devices/Watch6,3.json"
"share/devices/Watch6,4.json"
"share/devices/Watch6,6.json"
"share/devices/Watch6,7.json"
"share/devices/Watch6,8.json"
"share/devices/Watch6,9.json"
"share/devices/iBridge2,1.json"
"share/devices/iBridge2,10.json"
"share/devices/iBridge2,11.json"
"share/devices/iBridge2,12.json"
"share/devices/iBridge2,13.json"
"share/devices/iBridge2,14.json"
"share/devices/iBridge2,15.json"
"share/devices/iBridge2,16.json"
"share/devices/iBridge2,19.json"
"share/devices/iBridge2,20.json"
"share/devices/iBridge2,21.json"
"share/devices/iBridge2,22.json"
"share/devices/iBridge2,3.json"
"share/devices/iBridge2,4.json"
"share/devices/iBridge2,5.json"
"share/devices/iBridge2,6.json"
"share/devices/iBridge2,7.json"
"share/devices/iBridge2,8.json"
"share/devices/iPad11,1.json"
"share/devices/iPad11,2.json"
"share/devices/iPad11,3.json"
apple_data-1.0.533.dist-info/WHEEL
apple_data-1.0.533.dist-info/METADATA
apple_data-1.0.533.dist-info/RECORD
