Metadata-Version: 2.1
Name: apple-data
Version: 1.0.533
Summary: Static data from https://docs.hackdiffe.rent
Author: Rick Mark
Author-email: rickmark@outlook.com
Requires-Python: >=3.8,<4.0
Classifier: Programming Language :: Python :: 3
Classifier: Programming Language :: Python :: 3.8
Classifier: Programming Language :: Python :: 3.9
Classifier: Programming Language :: Python :: 3.10
Classifier: Programming Language :: Python :: 3.11
